arpscanner/__init__.py
arpscanner/arpscanner.py
arpscanner-0.1.dist-info/METADATA
arpscanner-0.1.dist-info/WHEEL
arpscanner-0.1.dist-info/entry_points.txt
arpscanner-0.1.dist-info/top_level.txt
arpscanner-0.1.dist-info/RECORD
