Metadata-Version: 2.4
Name: arpscanner
Version: 0.1
Requires-Dist: scapy
Dynamic: requires-dist
